xwmb/__init__.py
xwmb/budget.py
xwmb/version.py
xwmb-0.5.1.dist-info/METADATA
xwmb-0.5.1.dist-info/WHEEL
xwmb-0.5.1.dist-info/RECORD
