Metadata-Version: 2.4
Name: xwmb
Version: 0.5.1
Summary: Efficient and lazy computation of Water Mass Budgets in arbitrary sub-domains of C-grid ocean models
Project-URL: Homepage, https://github.com/hdrake/xwmb
Project-URL: Bugs/Issues/Features, https://github.com/hdrake/xwmb/issues
Author-email: "Henri F. Drake" <hfdrake@uci.edu>
Keywords: ocean mixing,water mass transformation
Classifier: License :: OSI Approved :: GNU General Public License v3 (GPLv3)
Classifier: Operating System :: OS Independent
Classifier: Programming Language :: Python :: 3
Requires-Python: >=3.8
Requires-Dist: regionate>=0.5.0
Requires-Dist: xwmt>=0.1.0
